[{
    "slno": 73,
    "moviename": "Captain Marvel",
    "starrating": 5,
    "year": 2019,
    "isFeatured": "FALSE"
  },
  {
    "slno": 64,
    "moviename": "Frozen",
    "starrating": 3,
    "year": 2013,
    "isFeatured": "FALSE"
  },
  {
    "slno": 14,
    "moviename": "Harry Potter and the Chamber of Secrets",
    "starrating": 1,
    "year": 2002,
    "isFeatured": "TRUE"
  },
  {
    "slno": 93,
    "moviename": "Harry Potter and the Deathly Hallows - Part 1",
    "starrating": 2,
    "year": 2010,
    "isFeatured": "FALSE"
  },
  {
    "slno": 11,
    "moviename": "Harry Potter and the Goblet of Fire",
    "starrating": 3,
    "year": 2005,
    "isFeatured": "FALSE"
  },
  {
    "slno": 8,
    "moviename": "Harry Potter and the Half-Blood Prince",
    "starrating": 4,
    "year": 2009,
    "isFeatured": "FALSE"
  },
  {
    "slno": 31,
    "moviename": "Ice Age: The Meltdown",
    "starrating": 1,
    "year": 2006,
    "isFeatured": "FALSE"
  },
  {
    "slno": 66,
    "moviename": "Incredibles 2",
    "starrating": 2,
    "year": 2018,
    "isFeatured": "FALSE"
  },
  {
    "slno": 54,
    "moviename": "Jurassic World",
    "starrating": 2,
    "year": 2015,
    "isFeatured": "FALSE"
  },
  {
    "slno": 47,
    "moviename": "King Kong",
    "starrating": 4,
    "year": 2005,
    "isFeatured": "FALSE"
  },
  {
    "slno": 40,
    "moviename": "Madagascar: Escape 2 Africa",
    "starrating": 4,
    "year": 2008,
    "isFeatured": "FALSE"
  },
  {
    "slno": 46,
    "moviename": "Night at the Museum",
    "starrating": 4,
    "year": 2006,
    "isFeatured": "FALSE"
  },
  {
    "slno": 43,
    "moviename": "Quantum of Solace",
    "starrating": 1,
    "year": 2008,
    "isFeatured": "FALSE"
  },
  {
    "slno": 81,
    "moviename": "Rogue One: A Star Wars Story",
    "starrating": 5,
    "year": 2016,
    "isFeatured": "FALSE"
  },
  {
    "slno": 89,
    "moviename": "Star Wars: The Rise of Skywalker",
    "starrating": 1,
    "year": 2019,
    "isFeatured": "FALSE"
  },
  {
    "slno": 77,
    "moviename": "The Dark Knight Rises",
    "starrating": 5,
    "year": 2012,
    "isFeatured": "FALSE"
  },
  {
    "slno": 67,
    "moviename": "The Fate of the Furious",
    "starrating": 3,
    "year": 2017,
    "isFeatured": "FALSE"
  },
  {
    "slno": 95,
    "moviename": "The Hobbit: The Battle of the Five Armies",
    "starrating": 3,
    "year": 2014,
    "isFeatured": "FALSE"
  },
  {
    "slno": 35,
    "moviename": "The Incredibles",
    "starrating": 3,
    "year": 2004,
    "isFeatured": "FALSE"
  },
  {
    "slno": 38,
    "moviename": "The Passion of the Christ",
    "starrating": 4,
    "year": 2004,
    "isFeatured": "FALSE"
  },
  {
    "slno": 100,
    "moviename": "The Secret Life of Pets",
    "starrating": 5,
    "year": 2016,
    "isFeatured": "FALSE"
  },
  {
    "slno": 87,
    "moviename": "Zootopia",
    "starrating": 4,
    "year": 2016,
    "isFeatured": "FALSE"
  },
  {
    "slno": 86,
    "moviename": "Alice in Wonderland",
    "starrating": 2,
    "year": 2010,
    "isFeatured": "FALSE"
  },
  {
    "slno": 53,
    "moviename": "Avengers: Infinity War",
    "starrating": 1,
    "year": 2018,
    "isFeatured": "FALSE"
  },
  {
    "slno": 84,
    "moviename": "Despicable Me 3",
    "starrating": 1,
    "year": 2017,
    "isFeatured": "FALSE"
  },
  {
    "slno": 16,
    "moviename": "Finding Nemo",
    "starrating": 1,
    "year": 2003,
    "isFeatured": "FALSE"
  },
  {
    "slno": 59,
    "moviename": "Frozen II",
    "starrating": 5,
    "year": 2019,
    "isFeatured": "FALSE"
  },
  {
    "slno": 57,
    "moviename": "Furious 7",
    "starrating": 5,
    "year": 2015,
    "isFeatured": "FALSE"
  },
  {
    "slno": 68,
    "moviename": "Iron Man 3",
    "starrating": 4,
    "year": 2013,
    "isFeatured": "FALSE"
  },
  {
    "slno": 79,
    "moviename": "Joker",
    "starrating": 5,
    "year": 2019,
    "isFeatured": "FALSE"
  },
  {
    "slno": 50,
    "moviename": "Madagascar",
    "starrating": 2,
    "year": 2005,
    "isFeatured": "FALSE"
  },
  {
    "slno": 83,
    "moviename": "Pirates of the Caribbean: On Stranger Tides",
    "starrating": 4,
    "year": 2011,
    "isFeatured": "FALSE"
  },
  {
    "slno": 32,
    "moviename": "Pirates of the Caribbean: The Curse of the Black Pearl",
    "starrating": 5,
    "year": 2003,
    "isFeatured": "FALSE"
  },
  {
    "slno": 98,
    "moviename": "Spider-Man: Homecoming",
    "starrating": 2,
    "year": 2017,
    "isFeatured": "FALSE"
  },
  {
    "slno": 52,
    "moviename": "Star Wars: The Force Awakens",
    "starrating": 1,
    "year": 2015,
    "isFeatured": "TRUE"
  },
  {
    "slno": 49,
    "moviename": "The Day After Tomorrow",
    "starrating": 3,
    "year": 2004,
    "isFeatured": "FALSE"
  },
  {
    "slno": 91,
    "moviename": "The Jungle Book",
    "starrating": 3,
    "year": 2016,
    "isFeatured": "FALSE"
  },
  {
    "slno": 30,
    "moviename": "The Twilight Saga: New Moon",
    "starrating": 5,
    "year": 2009,
    "isFeatured": "FALSE"
  },
  {
    "slno": 28,
    "moviename": "Transformers",
    "starrating": 3,
    "year": 2007,
    "isFeatured": "FALSE"
  },
  {
    "slno": 74,
    "moviename": "Transformers: Dark of the Moon",
    "starrating": 4,
    "year": 2011,
    "isFeatured": "FALSE"
  },
  {
    "slno": 29,
    "moviename": "Up",
    "starrating": 5,
    "year": 2009,
    "isFeatured": "TRUE"
  },
  {
    "slno": 44,
    "moviename": "I Am Legend",
    "starrating": 4,
    "year": 2007,
    "isFeatured": "FALSE"
  },
  {
    "slno": 22,
    "moviename": "Indiana Jones and the Kingdom of the Crystal Skull",
    "starrating": 1,
    "year": 2008,
    "isFeatured": "FALSE"
  },
  {
    "slno": 92,
    "moviename": "Jumanji: Welcome to the Jungle",
    "starrating": 2,
    "year": 2017,
    "isFeatured": "FALSE"
  },
  {
    "slno": 63,
    "moviename": "Jurassic World: Fallen Kingdom",
    "starrating": 4,
    "year": 2018,
    "isFeatured": "FALSE"
  },
  {
    "slno": 33,
    "moviename": "Star Wars: Episode II – Attack of the Clones",
    "starrating": 2,
    "year": 2002,
    "isFeatured": "FALSE"
  },
  {
    "slno": 17,
    "moviename": "Star Wars: Episode III – Revenge of the Sith",
    "starrating": 4,
    "year": 2005,
    "isFeatured": "FALSE"
  },
  {
    "slno": 56,
    "moviename": "The Avengers",
    "starrating": 2,
    "year": 2012,
    "isFeatured": "FALSE"
  },
  {
    "slno": 25,
    "moviename": "The Chronicles of Narnia",
    "starrating": 5,
    "year": 2005,
    "isFeatured": "FALSE"
  },
  {
    "slno": 88,
    "moviename": "The Hobbit: An Unexpected Journey",
    "starrating": 3,
    "year": 2012,
    "isFeatured": "FALSE"
  },
  {
    "slno": 80,
    "moviename": "Toy Story 3",
    "starrating": 3,
    "year": 2010,
    "isFeatured": "FALSE"
  },
  {
    "slno": 18,
    "moviename": "Transformers: Revenge of the Fallen",
    "starrating": 1,
    "year": 2009,
    "isFeatured": "FALSE"
  },
  {
    "slno": 58,
    "moviename": "Avengers: Age of Ultron",
    "starrating": 5,
    "year": 2015,
    "isFeatured": "FALSE"
  },
  {
    "slno": 51,
    "moviename": "Avengers: Endgame",
    "starrating": 1,
    "year": 2019,
    "isFeatured": "FALSE"
  },
  {
    "slno": 65,
    "moviename": "Beauty and the Beast",
    "starrating": 1,
    "year": 2017,
    "isFeatured": "FALSE"
  },
  {
    "slno": 70,
    "moviename": "Captain America: Civil War",
    "starrating": 3,
    "year": 2016,
    "isFeatured": "TRUE"
  },
  {
    "slno": 90,
    "moviename": "Despicable Me 2",
    "starrating": 4,
    "year": 2013,
    "isFeatured": "FALSE"
  },
  {
    "slno": 85,
    "moviename": "Finding Dory",
    "starrating": 2,
    "year": 2016,
    "isFeatured": "FALSE"
  },
  {
    "slno": 36,
    "moviename": "Hancock",
    "starrating": 4,
    "year": 2008,
    "isFeatured": "FALSE"
  },
  {
    "slno": 7,
    "moviename": "Harry Potter and the Order of the Phoenix",
    "starrating": 2,
    "year": 2007,
    "isFeatured": "FALSE"
  },
  {
    "slno": 5,
    "moviename": "Harry Potter and the Philosopher's Stone",
    "starrating": 2,
    "year": 2001,
    "isFeatured": "FALSE"
  },
  {
    "slno": 21,
    "moviename": "Harry Potter and the Prisoner of Azkaban",
    "starrating": 5,
    "year": 2004,
    "isFeatured": "FALSE"
  },
  {
    "slno": 99,
    "moviename": "Ice Age: Continental Drift",
    "starrating": 4,
    "year": 2012,
    "isFeatured": "FALSE"
  },
  {
    "slno": 39,
    "moviename": "Mamma Mia!",
    "starrating": 2,
    "year": 2008,
    "isFeatured": "FALSE"
  },
  {
    "slno": 3,
    "moviename": "Pirates of the Caribbean: Dead Man's Chest",
    "starrating": 2,
    "year": 2006,
    "isFeatured": "FALSE"
  },
  {
    "slno": 20,
    "moviename": "Shrek the Third",
    "starrating": 2,
    "year": 2007,
    "isFeatured": "FALSE"
  },
  {
    "slno": 75,
    "moviename": "Skyfall",
    "starrating": 2,
    "year": 2012,
    "isFeatured": "FALSE"
  },
  {
    "slno": 23,
    "moviename": "Spider-Man 2",
    "starrating": 5,
    "year": 2004,
    "isFeatured": "FALSE"
  },
  {
    "slno": 72,
    "moviename": "Spider-Man: Far From Home",
    "starrating": 3,
    "year": 2019,
    "isFeatured": "FALSE"
  },
  {
    "slno": 24,
    "moviename": "The Da Vinci Code",
    "starrating": 3,
    "year": 2006,
    "isFeatured": "FALSE"
  },
  {
    "slno": 4,
    "moviename": "The Dark Knight",
    "starrating": 2,
    "year": 2008,
    "isFeatured": "FALSE"
  },
  {
    "slno": 15,
    "moviename": "The Lord of the Rings: The Fellowship of the Ring",
    "starrating": 5,
    "year": 2001,
    "isFeatured": "FALSE"
  },
  {
    "slno": 2,
    "moviename": "The Lord of the Rings: The Return of the King",
    "starrating": 4,
    "year": 2003,
    "isFeatured": "FALSE"
  },
  {
    "slno": 78,
    "moviename": "Toy Story 4",
    "starrating": 3,
    "year": 2019,
    "isFeatured": "FALSE"
  },
  {
    "slno": 76,
    "moviename": "Transformers: Age of Extinction",
    "starrating": 4,
    "year": 2014,
    "isFeatured": "FALSE"
  },
  {
    "slno": 27,
    "moviename": 2012,
    "starrating": 5,
    "year": 2009,
    "isFeatured": "FALSE"
  },
  {
    "slno": 82,
    "moviename": "Aladdin",
    "starrating": 1,
    "year": 2019,
    "isFeatured": "FALSE"
  },
  {
    "slno": 71,
    "moviename": "Aquaman",
    "starrating": 1,
    "year": 2018,
    "isFeatured": "FALSE"
  },
  {
    "slno": 1,
    "moviename": "Avatar",
    "starrating": 2,
    "year": 2009,
    "isFeatured": "FALSE"
  },
  {
    "slno": 60,
    "moviename": "Black Panther",
    "starrating": 4,
    "year": 2018,
    "isFeatured": "FALSE"
  },
  {
    "slno": 96,
    "moviename": "Bohemian Rhapsody",
    "starrating": 3,
    "year": 2018,
    "isFeatured": "FALSE"
  },
  {
    "slno": 41,
    "moviename": "Casino Royale",
    "starrating": 5,
    "year": 2006,
    "isFeatured": "FALSE"
  },
  {
    "slno": 61,
    "moviename": "Harry Potter and the Deathly Hallows – Part 2",
    "starrating": 5,
    "year": 2011,
    "isFeatured": "FALSE"
  },
  {
    "slno": 13,
    "moviename": "Ice Age: Dawn of the Dinosaurs",
    "starrating": 4,
    "year": 2009,
    "isFeatured": "FALSE"
  },
  {
    "slno": 45,
    "moviename": "Iron Man",
    "starrating": 4,
    "year": 2008,
    "isFeatured": "FALSE"
  },
  {
    "slno": 34,
    "moviename": "Kung Fu Panda",
    "starrating": 5,
    "year": 2008,
    "isFeatured": "FALSE"
  },
  {
    "slno": 69,
    "moviename": "Minions",
    "starrating": 4,
    "year": 2015,
    "isFeatured": "FALSE"
  },
  {
    "slno": 48,
    "moviename": "Mission: Impossible 2",
    "starrating": 5,
    "year": 2000,
    "isFeatured": "FALSE"
  },
  {
    "slno": 6,
    "moviename": "Pirates of the Caribbean: At World's End",
    "starrating": 2,
    "year": 2007,
    "isFeatured": "TRUE"
  },
  {
    "slno": 37,
    "moviename": "Ratatouille",
    "starrating": 4,
    "year": 2007,
    "isFeatured": "FALSE"
  },
  {
    "slno": 10,
    "moviename": "Shrek 2",
    "starrating": 5,
    "year": 2004,
    "isFeatured": "FALSE"
  },
  {
    "slno": 97,
    "moviename": "Spectre",
    "starrating": 4,
    "year": 2015,
    "isFeatured": "FALSE"
  },
  {
    "slno": 19,
    "moviename": "Spider-Man",
    "starrating": 5,
    "year": 2002,
    "isFeatured": "FALSE"
  },
  {
    "slno": 12,
    "moviename": "Spider-Man 3",
    "starrating": 4,
    "year": 2007,
    "isFeatured": "FALSE"
  },
  {
    "slno": 62,
    "moviename": "Star Wars: The Last Jedi",
    "starrating": 5,
    "year": 2017,
    "isFeatured": "FALSE"
  },
  {
    "slno": 94,
    "moviename": "The Hobbit: The Desolation of Smaug",
    "starrating": 3,
    "year": 2013,
    "isFeatured": "FALSE"
  },
  {
    "slno": 55,
    "moviename": "The Lion King",
    "starrating": 5,
    "year": 2019,
    "isFeatured": "FALSE"
  },
  {
    "slno": 9,
    "moviename": "The Lord of the Rings: The Two Towers",
    "starrating": 2,
    "year": 2002,
    "isFeatured": "FALSE"
  },
  {
    "slno": 26,
    "moviename": "The Matrix Reloaded",
    "starrating": 3,
    "year": 2003,
    "isFeatured": "FALSE"
  },
  {
    "slno": 42,
    "moviename": "War of the Worlds",
    "starrating": 2,
    "year": 2005,
    "isFeatured": "FALSE"
  }
]
